[{"roundDetails": {"id": 80, "startTimestamp": 1727308800, "endTimestamp": 1728518400}, "analytic": {"nonBlacklistedVotes": 85699.97723063425, "totalDeposited": 1797.8579183677346, "dollarPerVote": 0.02097851103891628, "incentiveDirected": 0, "incentiveDirectedUSD": 0, "efficiency": 0.7382457418930712, "platform": "convex"}}, {"roundDetails": {"id": 79, "startTimestamp": 1726099200, "endTimestamp": 1727308800}, "analytic": {"nonBlacklistedVotes": 115609.62425813932, "totalDeposited": 1901.020985888306, "dollarPerVote": 0.01644344922048709, "incentiveDirected": 0, "incentiveDirectedUSD": 0, "efficiency": 1.0284798556146775, "platform": "convex"}}, {"roundDetails": {"id": 78, "startTimestamp": 1724889600, "endTimestamp": 1726099200}, "analytic": {"nonBlacklistedVotes": 163388.7830405723, "totalDeposited": 2273.015076315659, "dollarPerVote": 0.013911695980691828, "incentiveDirected": 0, "incentiveDirectedUSD": 0, "efficiency": 1.16765954517244, "platform": "convex"}}, {"roundDetails": {"id": 77, "startTimestamp": 1723680000, "endTimestamp": 1724889600}, "analytic": {"nonBlacklistedVotes": 240547.50524357273, "totalDeposited": 2730.173851821686, "dollarPerVote": 0.011349832329614794, "incentiveDirected": 0, "incentiveDirectedUSD": 0, "efficiency": 1.6587846701012317, "platform": "convex"}}, {"roundDetails": {"id": 76, "startTimestamp": 1722470400, "endTimestamp": 1723680000}, "analytic": {"nonBlacklistedVotes": 119746.12554829888, "totalDeposited": 1650.1093772368583, "dollarPerVote": 0.013780064863737881, "incentiveDirected": 0, "incentiveDirectedUSD": 0, "efficiency": 0.8796802651354929, "platform": "convex"}}, {"roundDetails": {"id": 75, "startTimestamp": 1721260800, "endTimestamp": 1722470400}, "analytic": {"nonBlacklistedVotes": 162996.2230061638, "totalDeposited": 2778.811150849102, "dollarPerVote": 0.017048316210026653, "incentiveDirected": 0, "incentiveDirectedUSD": 0, "efficiency": 0.8774295531530899, "platform": "convex"}}, {"roundDetails": {"id": 74, "startTimestamp": 1720051200, "endTimestamp": 1721260800}, "analytic": {"nonBlacklistedVotes": 157383.56036627377, "totalDeposited": 2591.491167143674, "dollarPerVote": 0.01646608553722243, "incentiveDirected": 0, "incentiveDirectedUSD": 0, "efficiency": 0.9765980204349712, "platform": "convex"}}, {"roundDetails": {"id": 73, "startTimestamp": 1718841600, "endTimestamp": 1720051200}, "analytic": {"nonBlacklistedVotes": 113140.23468261008, "totalDeposited": 2675.71358481354, "dollarPerVote": 0.023649531860347142, "incentiveDirected": 0, "incentiveDirectedUSD": 0, "efficiency": 0.6758524211614572, "platform": "convex"}}, {"roundDetails": {"id": 72, "startTimestamp": 1717632000, "endTimestamp": 1718841600}, "analytic": {"nonBlacklistedVotes": 116585.58225275704, "totalDeposited": 2408.260798325276, "dollarPerVote": 0.02065659193693588, "incentiveDirected": 0, "incentiveDirectedUSD": 0, "efficiency": 0.9412797240764288, "platform": "convex"}}, {"roundDetails": {"id": 71, "startTimestamp": 1716422400, "endTimestamp": 1717632000}, "analytic": {"nonBlacklistedVotes": 59022.81742778849, "totalDeposited": 1606.7690537076296, "dollarPerVote": 0.027222845735438372, "incentiveDirected": 0, "incentiveDirectedUSD": 0, "efficiency": 0.9303954901014557, "platform": "convex"}}, {"roundDetails": {"id": 70, "startTimestamp": 1715212800, "endTimestamp": 1716422400}, "analytic": {"nonBlacklistedVotes": 110930.7858168318, "totalDeposited": 2454.8244662508605, "dollarPerVote": 0.02212933450506923, "incentiveDirected": 0, "incentiveDirectedUSD": 0, "efficiency": 0.9909678540660012, "platform": "convex"}}, {"roundDetails": {"id": 69, "startTimestamp": 1714003200, "endTimestamp": 1715212800}, "analytic": {"nonBlacklistedVotes": 141103.4462698006, "totalDeposited": 3268.408718206355, "dollarPerVote": 0.02316320972031333, "incentiveDirected": 0, "incentiveDirectedUSD": 0, "efficiency": 0.934187463589862, "platform": "convex"}}, {"roundDetails": {"id": 68, "startTimestamp": 1712793600, "endTimestamp": 1714003200}, "analytic": {"nonBlacklistedVotes": 135306.8211713405, "totalDeposited": 3496.80373021386, "dollarPerVote": 0.025843514022000556, "incentiveDirected": 0, "incentiveDirectedUSD": 0, "efficiency": 0.8627667440124179, "platform": "convex"}}, {"roundDetails": {"id": 67, "startTimestamp": 1711584000, "endTimestamp": 1712793600}, "analytic": {"nonBlacklistedVotes": 82857.31450415634, "totalDeposited": 2880.63571556439, "dollarPerVote": 0.03476622109711135, "incentiveDirected": 0, "incentiveDirectedUSD": 0, "efficiency": 0.9092483571363879, "platform": "convex"}}, {"roundDetails": {"id": 66, "startTimestamp": 1710374400, "endTimestamp": 1711584000}, "analytic": {"nonBlacklistedVotes": 66483.01761532396, "totalDeposited": 2648.9070950856744, "dollarPerVote": 0.039843364367310494, "incentiveDirected": 0, "incentiveDirectedUSD": 0, "efficiency": 0.8834420514454495, "platform": "convex"}}, {"roundDetails": {"id": 65, "startTimestamp": 1709164800, "endTimestamp": 1710374400}, "analytic": {"nonBlacklistedVotes": 40712.31775278276, "totalDeposited": 1566.2660635406721, "dollarPerVote": 0.0384715523456931, "incentiveDirected": 0, "incentiveDirectedUSD": 0, "efficiency": 1.076510906631896, "platform": "convex"}}, {"roundDetails": {"id": 64, "startTimestamp": 1707955200, "endTimestamp": 1709164800}, "analytic": {"nonBlacklistedVotes": 28525.536230256384, "totalDeposited": 801.0384484093835, "dollarPerVote": 0.02808145101790375, "incentiveDirected": 0, "incentiveDirectedUSD": 0, "efficiency": 1.014598958462799, "platform": "convex"}}, {"roundDetails": {"id": 63, "startTimestamp": 1706745600, "endTimestamp": 1707955200}, "analytic": {"nonBlacklistedVotes": 47432.19104862626, "totalDeposited": 1235.174598366213, "dollarPerVote": 0.026040850550208487, "incentiveDirected": 0, "incentiveDirectedUSD": 0, "efficiency": 0.97355556707088, "platform": "convex"}}, {"roundDetails": {"id": 62, "startTimestamp": 1705536000, "endTimestamp": 1706745600}, "analytic": {"nonBlacklistedVotes": 45383.78848377939, "totalDeposited": 1593.629023455003, "dollarPerVote": 0.035114499619717326, "incentiveDirected": 0, "incentiveDirectedUSD": 0, "efficiency": 0.6915757211159722, "platform": "convex"}}, {"roundDetails": {"id": 61, "startTimestamp": 1704326400, "endTimestamp": 1705536000}, "analytic": {"nonBlacklistedVotes": 50053.38890069083, "totalDeposited": 862.625643063627, "dollarPerVote": 0.0172341106568255, "incentiveDirected": 0, "incentiveDirectedUSD": 0, "efficiency": 1.7850505328841002, "platform": "convex"}}, {"roundDetails": {"id": 60, "startTimestamp": 1703116800, "endTimestamp": 1704326400}, "analytic": {"nonBlacklistedVotes": 58683.91180489453, "totalDeposited": 1757.8003694117933, "dollarPerVote": 0.029953701369736976, "incentiveDirected": 0, "incentiveDirectedUSD": 0, "efficiency": 1.2217169035969486, "platform": "convex"}}, {"roundDetails": {"id": 59, "startTimestamp": 1701907200, "endTimestamp": 1703116800}, "analytic": {"nonBlacklistedVotes": 54165.95149479298, "totalDeposited": 1558.7512105361814, "dollarPerVote": 0.0287773253772903, "incentiveDirected": 0, "incentiveDirectedUSD": 0, "efficiency": 1.1968603645882334, "platform": "convex"}}, {"roundDetails": {"id": 58, "startTimestamp": 1700697600, "endTimestamp": 1701907200}, "analytic": {"nonBlacklistedVotes": 62106.95745863705, "totalDeposited": 1866.3730200798864, "dollarPerVote": 0.03005094914402919, "incentiveDirected": 0, "incentiveDirectedUSD": 0, "efficiency": 1.0625541526981361, "platform": "convex"}}, {"roundDetails": {"id": 57, "startTimestamp": 1699488000, "endTimestamp": 1700697600}, "analytic": {"nonBlacklistedVotes": 65656.89773735708, "totalDeposited": 1995.8836243251853, "dollarPerVote": 0.030398689141682964, "incentiveDirected": 0, "incentiveDirectedUSD": 0, "efficiency": 1.1719091142682012, "platform": "convex"}}, {"roundDetails": {"id": 56, "startTimestamp": 1698278400, "endTimestamp": 1699488000}, "analytic": {"nonBlacklistedVotes": 64377.98230374869, "totalDeposited": 1631.9554584511498, "dollarPerVote": 0.025349590031437223, "incentiveDirected": 0, "incentiveDirectedUSD": 0, "efficiency": 1.182450774081322, "platform": "convex"}}, {"roundDetails": {"id": 55, "startTimestamp": 1697068800, "endTimestamp": 1698278400}, "analytic": {"nonBlacklistedVotes": 80163.046821385, "totalDeposited": 1874.6735114941353, "dollarPerVote": 0.023385756727425572, "incentiveDirected": 0, "incentiveDirectedUSD": 0, "efficiency": 1.036657039055298, "platform": "convex"}}, {"roundDetails": {"id": 54, "startTimestamp": 1695859200, "endTimestamp": 1697068800}, "analytic": {"nonBlacklistedVotes": 79659.50857968029, "totalDeposited": 1750.1079597282053, "dollarPerVote": 0.021969856341476683, "incentiveDirected": 0, "incentiveDirectedUSD": 0, "efficiency": 1.2228481110379597, "platform": "convex"}}, {"roundDetails": {"id": 53, "startTimestamp": 1694649600, "endTimestamp": 1695859200}, "analytic": {"nonBlacklistedVotes": 66158.59345266827, "totalDeposited": 1710.768681366266, "dollarPerVote": 0.025858601159503163, "incentiveDirected": 0, "incentiveDirectedUSD": 0, "efficiency": 0.9302809141917703, "platform": "convex"}}, {"roundDetails": {"id": 81, "startTimestamp": 1728518400, "endTimestamp": 1729728000}, "analytic": {"nonBlacklistedVotes": 125792.62521784108, "totalDeposited": 2284.7564718927274, "dollarPerVote": 0.01816288091560301, "incentiveDirected": 0, "incentiveDirectedUSD": 0, "efficiency": 0.8987522262652888, "platform": "convex"}}, {"roundDetails": {"id": 82, "startTimestamp": 1729728000, "endTimestamp": 1730937600}, "analytic": {"nonBlacklistedVotes": 138776.7359630023, "totalDeposited": 1791.3982567680641, "dollarPerVote": 0.012908491069033707, "incentiveDirected": 0, "incentiveDirectedUSD": 0, "efficiency": 1.2827640488620957, "platform": "convex"}}, {"roundDetails": {"id": 83, "startTimestamp": 1730937600, "endTimestamp": 1732147200}, "analytic": {"nonBlacklistedVotes": 120052.62628648875, "totalDeposited": 2082.730689787924, "dollarPerVote": 0.017348480863865312, "incentiveDirected": 0, "incentiveDirectedUSD": 0, "efficiency": 1.1372394017753993, "platform": "convex"}}, {"roundDetails": {"id": 84, "startTimestamp": 1732147200, "endTimestamp": 1733356800}, "analytic": {"nonBlacklistedVotes": 129135.26109267544, "totalDeposited": 2742.0717524272854, "dollarPerVote": 0.021234105458302403, "incentiveDirected": 0, "incentiveDirectedUSD": 0, "efficiency": 1.4487920263454461, "platform": "convex"}}, {"roundDetails": {"id": 85, "startTimestamp": 1733356800, "endTimestamp": 1734566400}, "analytic": {"nonBlacklistedVotes": 49207.14327205974, "totalDeposited": 1955.3591199229431, "dollarPerVote": 0.03973730214558531, "incentiveDirected": 0, "incentiveDirectedUSD": 0, "efficiency": 1.7267789393298327, "platform": "convex"}}, {"roundDetails": {"id": 86, "startTimestamp": 1734566400, "endTimestamp": 1735776000}, "analytic": {"nonBlacklistedVotes": 79650.1122178059, "totalDeposited": 2690.6108841929386, "dollarPerVote": 0.03378037782087956, "incentiveDirected": 0, "incentiveDirectedUSD": 0, "efficiency": 1.8528798191261633, "platform": "convex"}}, {"roundDetails": {"id": 87, "startTimestamp": 1735776000, "endTimestamp": 1736985600}, "analytic": {"nonBlacklistedVotes": 80331.76103379604, "totalDeposited": 3002.705539347628, "dollarPerVote": 0.037378808838566015, "incentiveDirected": 0, "incentiveDirectedUSD": 0, "efficiency": 1.4567458309462977, "platform": "convex"}}, {"roundDetails": {"id": 88, "startTimestamp": 1736985600, "endTimestamp": 1738195200}, "analytic": {"nonBlacklistedVotes": 62977.887991884665, "totalDeposited": 2113.3894878139376, "dollarPerVote": 0.03355764309032194, "incentiveDirected": 0, "incentiveDirectedUSD": 0, "efficiency": 1.5449106878093548, "platform": "convex"}}, {"roundDetails": {"id": 89, "startTimestamp": 1738195200, "endTimestamp": 1739404800}, "analytic": {"nonBlacklistedVotes": 50222.65438674901, "totalDeposited": 1358.4208339572651, "dollarPerVote": 0.027047969697031337, "incentiveDirected": 0, "incentiveDirectedUSD": 0, "efficiency": 1.3010632327303484, "platform": "convex"}}, {"roundDetails": {"id": 90, "startTimestamp": 1739404800, "endTimestamp": 1740614400}, "analytic": {"nonBlacklistedVotes": 88802.10148530925, "totalDeposited": 2015.5965330879415, "dollarPerVote": 0.02269762200865693, "incentiveDirected": 0, "incentiveDirectedUSD": 0, "efficiency": 1.5497089191314672, "platform": "convex"}}, {"roundDetails": {"id": 91, "startTimestamp": 1740614400, "endTimestamp": 1741824000}, "analytic": {"nonBlacklistedVotes": 77586.09434848712, "totalDeposited": 1460.3971936528965, "dollarPerVote": 0.0188229244675386, "incentiveDirected": 0, "incentiveDirectedUSD": 0, "efficiency": 1.6050441024205921, "platform": "convex"}}, {"roundDetails": {"id": 92, "startTimestamp": 1741824000, "endTimestamp": 1743033600}, "analytic": {"nonBlacklistedVotes": 90098.07335295208, "totalDeposited": 1663.8153094922238, "dollarPerVote": 0.018466713521990186, "incentiveDirected": 0, "incentiveDirectedUSD": 0, "efficiency": 1.7555745341691122, "platform": "convex"}}, {"roundDetails": {"id": 93, "startTimestamp": 1743033600, "endTimestamp": 1744243200}, "analytic": {"nonBlacklistedVotes": 42898.52828645749, "totalDeposited": 1055.9673167782328, "dollarPerVote": 0.02461546721899054, "incentiveDirected": 0, "incentiveDirectedUSD": 0, "efficiency": 1.3853185135826867, "platform": "convex"}}, {"roundDetails": {"id": 94, "startTimestamp": 1744243200, "endTimestamp": 1745452800}, "analytic": {"gauge": "0x8133e6b0b2420bba10574a6668ea275f5e7ed253", "nonBlacklistedVotes": 30592.41900634624, "nonBlacklistedVotesBreakdowns": [], "totalDeposited": 818.1667187587303, "dollarPerVote": 0.02674410018341491, "incentiveDirected": 0.0, "incentiveDirectedUSD": 0.0, "efficiency": 1.6716934959240903, "platform": "votium"}}, {"roundDetails": {"id": 95, "startTimestamp": 1745452800, "endTimestamp": 1746662400}, "analytic": {"gauge": "0x8133e6b0b2420bba10574a6668ea275f5e7ed253", "nonBlacklistedVotes": 26545.576580883437, "nonBlacklistedVotesBreakdowns": [], "totalDeposited": 795.1612614624429, "dollarPerVote": 0.02995456734720433, "incentiveDirected": 0.0, "incentiveDirectedUSD": 0.0, "efficiency": 1.7475627563163698, "platform": "votium"}}, {"roundDetails": {"id": 96, "startTimestamp": 1746662400, "endTimestamp": 1747872000}, "analytic": {"gauge": "0x8133e6b0b2420bba10574a6668ea275f5e7ed253", "nonBlacklistedVotes": 24062.40182184097, "nonBlacklistedVotesBreakdowns": [], "totalDeposited": 872.6422962136935, "dollarPerVote": 0.03626580183785366, "incentiveDirected": 0.0, "incentiveDirectedUSD": 0.0, "efficiency": 1.3912520664394437, "platform": "votium"}}, {"roundDetails": {"id": 97, "startTimestamp": 1747872000, "endTimestamp": 1749081600}, "analytic": {"gauge": "0x8133e6b0b2420bba10574a6668ea275f5e7ed253", "nonBlacklistedVotes": 32105.962666138814, "nonBlacklistedVotesBreakdowns": [], "totalDeposited": 856.5514617107264, "dollarPerVote": 0.026678890479558966, "incentiveDirected": 0.0, "incentiveDirectedUSD": 0.0, "efficiency": 1.9776874505563162, "platform": "votium"}}, {"roundDetails": {"id": 98, "startTimestamp": 1749081600, "endTimestamp": 1750291200}, "analytic": {"gauge": "0x8133e6b0b2420bba10574a6668ea275f5e7ed253", "nonBlacklistedVotes": 23608.635353499223, "nonBlacklistedVotesBreakdowns": [], "totalDeposited": 792.7488146244436, "dollarPerVote": 0.03357876483559411, "incentiveDirected": 0.0, "incentiveDirectedUSD": 0.0, "efficiency": 1.4585392246845308, "platform": "votium"}}]