{"totalDepositedUSD": 859777.4581982755, "globalAverageDollarPerVote": 0.0316698369027617, "globalAverageEfficiency": 2.1666526626412543, "analytics": [{"gauge": "0xF20bd4D5A4112d5f9c64aDF53726F3ef1b7d0D61", "nonBlacklistedVotes": 30664.533830794426, "nonBlacklistedVotesBreakdowns": [], "totalDeposited": 1233.1090320529863, "dollarPerVote": 0.040212873897161744, "efficiency": 1.7063574373286952, "platform": "convex"}, {"gauge": "0xC798130644b8962a357dfBe8BB30b19b681AA7D4", "nonBlacklistedVotes": 32250.41048410515, "nonBlacklistedVotesBreakdowns": [], "totalDeposited": 0.0, "dollarPerVote": 0.0, "efficiency": -1, "platform": "convex"}, {"gauge": "0xa5Dc66685bD13A0924505807c29F8C65dDa0d207", "nonBlacklistedVotes": 32011.840158361632, "nonBlacklistedVotesBreakdowns": [], "totalDeposited": 0.0, "dollarPerVote": 0.0, "efficiency": -1, "platform": "convex"}, {"gauge": "0x8605dc0C339a2e7e85EEA043bD29d42DA2c6D784", "nonBlacklistedVotes": 63999.40290249183, "nonBlacklistedVotesBreakdowns": [], "totalDeposited": 722.1975433900003, "dollarPerVote": 0.011284441895345892, "efficiency": 6.080720436788568, "platform": "convex"}, {"gauge": "0x44f30D79f62a3D5340030d64806cD73239889F07", "nonBlacklistedVotes": 43023.761687342754, "nonBlacklistedVotesBreakdowns": [], "totalDeposited": 0.0, "dollarPerVote": 0.0, "efficiency": -1, "platform": "convex"}, {"gauge": "0x41af8cC0811DD07F167752B821CF5B11DBa7Ca85", "nonBlacklistedVotes": 12882416.140293833, "nonBlacklistedVotesBreakdowns": [], "totalDeposited": 0.0, "dollarPerVote": 0.0, "efficiency": -1, "platform": "convex"}, {"gauge": "0x16A3a047fC1D388d5846a73ACDb475b11228c299", "nonBlacklistedVotes": 487966.3086347959, "nonBlacklistedVotesBreakdowns": [], "totalDeposited": 19241.78358912, "dollarPerVote": 0.039432606818600974, "efficiency": 1.7401217415434713, "platform": "convex"}, {"gauge": "0x7E1444BA99dcdFfE8fBdb42C02F0005D14f13BE1", "nonBlacklistedVotes": 2228381.1827471023, "nonBlacklistedVotesBreakdowns": [], "totalDeposited": 80507.712, "dollarPerVote": 0.03612833954231823, "efficiency": 1.8992717993698292, "platform": "convex"}, {"gauge": "0xaa386EF96A910Ee2F9cbEf7B139e99A88DF3b2ba", "nonBlacklistedVotes": 106831.31326337776, "nonBlacklistedVotesBreakdowns": [], "totalDeposited": 829.632, "dollarPerVote": 0.007765812987383741, "efficiency": 8.835847136965342, "platform": "convex"}, {"gauge": "0xc2075702490F0426E84E00d8B328119027813AC5", "nonBlacklistedVotes": 800438.030895262, "nonBlacklistedVotesBreakdowns": [], "totalDeposited": 30925.785259268825, "dollarPerVote": 0.038636076829931996, "efficiency": 1.7759964799951886, "platform": "convex"}, {"gauge": "0xfB18127c1471131468a1AaD4785c19678e521D86", "nonBlacklistedVotes": 4562614.105066782, "nonBlacklistedVotesBreakdowns": [], "totalDeposited": 156104.448, "dollarPerVote": 0.03421381786959499, "efficiency": 2.005550409846592, "platform": "convex"}, {"gauge": "0x0c58c509305a8a7fE9a6a60CEaAC6185B96ECBb7", "nonBlacklistedVotes": 64280.46564860574, "nonBlacklistedVotesBreakdowns": [], "totalDeposited": 2227.2, "dollarPerVote": 0.03464816219868669, "efficiency": 1.9804091211909585, "platform": "convex"}, {"gauge": "0x070EBC9F46d0a6A523D31eb4aE7901C56AD97ae2", "nonBlacklistedVotes": 225853.1652761181, "nonBlacklistedVotesBreakdowns": [], "totalDeposited": 8919.936, "dollarPerVote": 0.039494403317725836, "efficiency": 1.7373989904029272, "platform": "convex"}, {"gauge": "0x724476f141ED2DE4DA22eBDF435905dEf1118317", "nonBlacklistedVotes": 177670.59692542008, "nonBlacklistedVotesBreakdowns": [], "totalDeposited": 6336.384, "dollarPerVote": 0.03566366134661997, "efficiency": 1.92401828247189, "platform": "convex"}, {"gauge": "0x13E58C7b1147385D735a06D14F0456E54C2dEBC8", "nonBlacklistedVotes": 138480.4282024274, "nonBlacklistedVotesBreakdowns": [], "totalDeposited": 5484.48, "dollarPerVote": 0.039604730222114255, "efficiency": 1.7325591177103545, "platform": "convex"}, {"gauge": "0xf792934842e86f964bDF19A439797a6e3c9fE17B", "nonBlacklistedVotes": 33595.04263870372, "nonBlacklistedVotesBreakdowns": [], "totalDeposited": 0.0, "dollarPerVote": 0.0, "efficiency": -1, "platform": "convex"}, {"gauge": "0xB1A829a05E618F7C4f50Cb86f8F64Fb86e42dE5a", "nonBlacklistedVotes": 59769.65487079194, "nonBlacklistedVotesBreakdowns": [], "totalDeposited": 0.0, "dollarPerVote": 0.0, "efficiency": -1, "platform": "convex"}, {"gauge": "0x2932a86df44Fe8D2A706d8e9c5d51c24883423F5", "nonBlacklistedVotes": 95556.86147341604, "nonBlacklistedVotesBreakdowns": [], "totalDeposited": 3777.7679999999996, "dollarPerVote": 0.03953424109739075, "efficiency": 1.735648251897559, "platform": "convex"}, {"gauge": "0x4E21418095d32d15c6e2B96A9910772613A50d50", "nonBlacklistedVotes": 205836.07223045363, "nonBlacklistedVotesBreakdowns": [], "totalDeposited": 8121.945599999999, "dollarPerVote": 0.039458319972733864, "efficiency": 1.7389877850399704, "platform": "convex"}, {"gauge": "0x821529Bb07c83803C9CC7763e5974386e9eFEdC7", "nonBlacklistedVotes": 386320.5184887024, "nonBlacklistedVotesBreakdowns": [], "totalDeposited": 13780.9296, "dollarPerVote": 0.03567226937339858, "efficiency": 1.923554000238408, "platform": "convex"}, {"gauge": "0x9755e37A291a37d8a0AB0828699A59b445477514", "nonBlacklistedVotes": 192658.733222106, "nonBlacklistedVotesBreakdowns": [], "totalDeposited": 7612.8, "dollarPerVote": 0.039514429855736714, "efficiency": 1.736518449115899, "platform": "convex"}, {"gauge": "0x96424E6b5eaafe0c3B36CA82068d574D44BE4e3c", "nonBlacklistedVotes": 134781.26852492205, "nonBlacklistedVotesBreakdowns": [], "totalDeposited": 5312.5632000000005, "dollarPerVote": 0.039416183406952195, "efficiency": 1.7408467923528128, "platform": "convex"}, {"gauge": "0xB53c23D2CC6219adf78ea22Bfd38bFfc50eC54cB", "nonBlacklistedVotes": 2133811.5907963244, "nonBlacklistedVotesBreakdowns": [], "totalDeposited": 72092.0448, "dollarPerVote": 0.03378557184287097, "efficiency": 2.030971586626016, "platform": "convex"}, {"gauge": "0x0E83dF148F69965BfE752250835854b0dBeeaf01", "nonBlacklistedVotes": 114644.35699628315, "nonBlacklistedVotesBreakdowns": [], "totalDeposited": 4553.6256, "dollarPerVote": 0.03971957904694456, "efficiency": 1.7275494377642786, "platform": "convex"}, {"gauge": "0xB7A3C519889a916C5ecB54101E69ECf11DE60d0b", "nonBlacklistedVotes": 174503.565386607, "nonBlacklistedVotesBreakdowns": [], "totalDeposited": 209.34684131823158, "dollarPerVote": 0.0011996708540277126, "efficiency": 57.19696883558514, "platform": "convex"}, {"gauge": "0x4B43fEaB8f5ccD38Ac0831DD7eC797330114F058", "nonBlacklistedVotes": 1399.2853957610853, "nonBlacklistedVotesBreakdowns": [], "totalDeposited": 55.3358950292186, "dollarPerVote": 0.039545824745152044, "efficiency": 1.7351398508687006, "platform": "convex"}, {"gauge": "0x415F30505368fa1dB82Feea02EB778be04e75907", "nonBlacklistedVotes": 1782289.141264967, "nonBlacklistedVotesBreakdowns": [], "totalDeposited": 65070.665081531195, "dollarPerVote": 0.03650960081333815, "efficiency": 1.8794381456429035, "platform": "convex"}, {"gauge": "0x740BA8aa0052E07b925908B380248cb03f3DE5cB", "nonBlacklistedVotes": 3266289.200658073, "nonBlacklistedVotesBreakdowns": [], "totalDeposited": 72321.57384179826, "dollarPerVote": 0.02214181580345896, "efficiency": 3.0990022254662404, "platform": "convex"}, {"gauge": "0xBE266d68Ce3dDFAb366Bb866F4353B6FC42BA43c", "nonBlacklistedVotes": 73983.39885842623, "nonBlacklistedVotesBreakdowns": [], "totalDeposited": 2923.4271180791516, "dollarPerVote": 0.03951463656966325, "efficiency": 1.736509364822627, "platform": "convex"}, {"gauge": "0x8133e6B0B2420bBa10574A6668ea275f5E7Ed253", "nonBlacklistedVotes": 49207.14327205974, "nonBlacklistedVotesBreakdowns": [], "totalDeposited": 1955.3591199229431, "dollarPerVote": 0.03973730214558531, "efficiency": 1.7267789393298327, "platform": "convex"}, {"gauge": "0x06B30D5F2341C2FB3F6B48b109685997022Bd272", "nonBlacklistedVotes": 324534.6569318444, "nonBlacklistedVotesBreakdowns": [], "totalDeposited": 310.07880953202095, "dollarPerVote": 0.0009554566913238504, "efficiency": 71.81648009153467, "platform": "convex"}, {"gauge": "0xd5f2e6612E41bE48461FDBA20061E3c778Fe6EC4", "nonBlacklistedVotes": 409883.66371837666, "nonBlacklistedVotesBreakdowns": [], "totalDeposited": 16186.43954644018, "dollarPerVote": 0.03949032610765765, "efficiency": 1.737578369540917, "platform": "convex"}, {"gauge": "0xa47d0837F84Fb2d1aA08077D10d10101316a959d", "nonBlacklistedVotes": 12998.277114264823, "nonBlacklistedVotesBreakdowns": [], "totalDeposited": 175.7705447074697, "dollarPerVote": 0.013522603277519921, "efficiency": 5.074284517749123, "platform": "convex"}, {"gauge": "0xF184d80915Ba7d835D941BA70cDdf93DE36517ee", "nonBlacklistedVotes": 18073.319424001784, "nonBlacklistedVotesBreakdowns": [], "totalDeposited": 731.2496515011575, "dollarPerVote": 0.04046017415760611, "efficiency": 1.6959278569462972, "platform": "convex"}, {"gauge": "0x4B092818708A721cB187dFACF41f440ADb79044D", "nonBlacklistedVotes": 95737.87214066318, "nonBlacklistedVotesBreakdowns": [], "totalDeposited": 3798.2016000000003, "dollarPerVote": 0.03967292686868453, "efficiency": 1.729580897267893, "platform": "convex"}, {"gauge": "0x8f8E854EF0dc76D88D2e217D3c2653672d13b252", "nonBlacklistedVotes": 29832.675345249205, "nonBlacklistedVotesBreakdowns": [], "totalDeposited": 505.95840000000004, "dollarPerVote": 0.01695987349926271, "efficiency": 4.045875486852297, "platform": "convex"}, {"gauge": "0x48100238C4a3CF44cFbF6C7693eD5C216881fAcE", "nonBlacklistedVotes": 360955.10199527256, "nonBlacklistedVotesBreakdowns": [], "totalDeposited": 7027.200000000001, "dollarPerVote": 0.019468349279883668, "efficiency": 3.524568799558383, "platform": "convex"}, {"gauge": "0x541f57aB2032A042CE6B02Fd435347fBaE1F6d0A", "nonBlacklistedVotes": 150255.7602917115, "nonBlacklistedVotesBreakdowns": [], "totalDeposited": 3513.6000000000004, "dollarPerVote": 0.023384128456563538, "efficiency": 2.934363646617887, "platform": "convex"}, {"gauge": "0x59005665c5060D3abEE291A21DE0375cf1BBed03", "nonBlacklistedVotes": 210804.05931826585, "nonBlacklistedVotesBreakdowns": [], "totalDeposited": 5270.400000000001, "dollarPerVote": 0.02500141608773721, "efficiency": 2.744545997314076, "platform": "convex"}, {"gauge": "0x64100c172D5DC8007E3ee701ECD99468619B6583", "nonBlacklistedVotes": 59665.35069049841, "nonBlacklistedVotesBreakdowns": [], "totalDeposited": 527.04, "dollarPerVote": 0.00883326744753266, "efficiency": 7.768080934756411, "platform": "convex"}, {"gauge": "0x6b794C5e3188c2C8C1412DBF38Fd70e9b20446a7", "nonBlacklistedVotes": 89498.0260357476, "nonBlacklistedVotesBreakdowns": [], "totalDeposited": 351.36, "dollarPerVote": 0.00392589664334785, "efficiency": 17.478182103201924, "platform": "convex"}, {"gauge": "0x72Bd89F2E3470fA5d188cF04eda17E8145eb4BF1", "nonBlacklistedVotes": 59665.35069049841, "nonBlacklistedVotesBreakdowns": [], "totalDeposited": 527.04, "dollarPerVote": 0.00883326744753266, "efficiency": 7.768080934756411, "platform": "convex"}, {"gauge": "0x7bA1e40dAe22847E6c521bA297d40fF1c5fD97dd", "nonBlacklistedVotes": 330134.7606992626, "nonBlacklistedVotesBreakdowns": [], "totalDeposited": 5270.400000000001, "dollarPerVote": 0.015964389780817687, "efficiency": 4.298162184265356, "platform": "convex"}, {"gauge": "0x86A79cEE2734E5357FF6B5495c4a30915921223a", "nonBlacklistedVotes": 212440.48607247812, "nonBlacklistedVotesBreakdowns": [], "totalDeposited": 3513.6000000000004, "dollarPerVote": 0.016539220300980054, "efficiency": 4.148776979935195, "platform": "convex"}, {"gauge": "0x8882eB84d0c4894753C0450f2D514E39883c0C82", "nonBlacklistedVotes": 43526.6351060828, "nonBlacklistedVotesBreakdowns": [], "totalDeposited": 1756.8000000000002, "dollarPerVote": 0.040361493502043974, "efficiency": 1.7000742662634123, "platform": "convex"}, {"gauge": "0x98a6C35546be6F7c545c99EfB48F4673eD2c99fc", "nonBlacklistedVotes": 43526.6351060828, "nonBlacklistedVotesBreakdowns": [], "totalDeposited": 1756.8000000000002, "dollarPerVote": 0.040361493502043974, "efficiency": 1.7000742662634123, "platform": "convex"}, {"gauge": "0xAA6dDbA00DE48D41E41543eF0a78AB31aae4dE8d", "nonBlacklistedVotes": 59665.35069049841, "nonBlacklistedVotesBreakdowns": [], "totalDeposited": 351.36, "dollarPerVote": 0.005888844965021774, "efficiency": 11.652121402134616, "platform": "convex"}, {"gauge": "0xBd4Af2a6510b988878805956e5111839e55de069", "nonBlacklistedVotes": 269586.4616727083, "nonBlacklistedVotesBreakdowns": [], "totalDeposited": 3513.6000000000004, "dollarPerVote": 0.01303329543404776, "efficiency": 5.26478792704481, "platform": "convex"}, {"gauge": "0xD1D981dDD0c9A0469E7d8cEE877f83B5877D7260", "nonBlacklistedVotes": 30470.11726482284, "nonBlacklistedVotesBreakdowns": [], "totalDeposited": 1054.08, "dollarPerVote": 0.03459389377594929, "efficiency": 1.9835158451717236, "platform": "convex"}, {"gauge": "0xE049AA6fbd64210bDEddC15F5a861084E6eE8b57", "nonBlacklistedVotes": 43526.6351060828, "nonBlacklistedVotesBreakdowns": [], "totalDeposited": 1756.8000000000002, "dollarPerVote": 0.040361493502043974, "efficiency": 1.7000742662634123, "platform": "convex"}, {"gauge": "0xcde3Cdf332E35653A7595bA555c9fDBA3c78Ec04", "nonBlacklistedVotes": 0, "nonBlacklistedVotesBreakdowns": [], "totalDeposited": 1756.8000000000002, "dollarPerVote": 0, "efficiency": -1, "platform": "convex"}, {"gauge": "0xf868B47717F4739EE142b3BE6EE0f84Da868E917", "nonBlacklistedVotes": 182159.0094867227, "nonBlacklistedVotesBreakdowns": [], "totalDeposited": 5270.400000000001, "dollarPerVote": 0.028932963650003553, "efficiency": 2.37160414262555, "platform": "convex"}, {"gauge": "0xFC6891C8482aeF6AEF71a09A09ce14432617A403", "nonBlacklistedVotes": 119330.70138099682, "nonBlacklistedVotesBreakdowns": [], "totalDeposited": 2635.2000000000003, "dollarPerVote": 0.022083168618831656, "efficiency": 3.107232373902564, "platform": "convex"}, {"gauge": "0x88342AB58Ae18391F1e26A8287aB418B009322e6", "nonBlacklistedVotes": 68668.2406640985, "nonBlacklistedVotesBreakdowns": [], "totalDeposited": 0.0, "dollarPerVote": 0.0, "efficiency": -1, "platform": "convex"}, {"gauge": "0x5A8fa46ebb404494D718786e55c4E043337B10bF", "nonBlacklistedVotes": 24790.553448186227, "nonBlacklistedVotesBreakdowns": [], "totalDeposited": 0.0, "dollarPerVote": 0.0, "efficiency": -1, "platform": "convex"}, {"gauge": "0x7970489a543FB237ABab63d62524d8A5CE165B86", "nonBlacklistedVotes": 141600.40225445392, "nonBlacklistedVotesBreakdowns": [], "totalDeposited": 5568.0, "dollarPerVote": 0.03932192219337331, "efficiency": 1.745019892805408, "platform": "convex"}, {"gauge": "0x4e227d29b33B77113F84bcC189a6F886755a1f24", "nonBlacklistedVotes": 264844.62646082026, "nonBlacklistedVotesBreakdowns": [], "totalDeposited": 10441.601999999999, "dollarPerVote": 0.03942538740367713, "efficiency": 1.7404403854858015, "platform": "convex"}, {"gauge": "0x1a38A26f1EB658f0CAef3A5A722e56d44511279B", "nonBlacklistedVotes": 963157.800900842, "nonBlacklistedVotesBreakdowns": [], "totalDeposited": 28800.0, "dollarPerVote": 0.02990164225744042, "efficiency": 2.2947748441378266, "platform": "convex"}, {"gauge": "0x58215F083882A5eb7056Ac34a0fdDA9D3b5665d2", "nonBlacklistedVotes": 754856.5510335464, "nonBlacklistedVotesBreakdowns": [], "totalDeposited": 29698.444799999997, "dollarPerVote": 0.0393431636240515, "efficiency": 1.7440777540531898, "platform": "convex"}, {"gauge": "0xABaD903647511a0EC755a118849f733f7d2Ba002", "nonBlacklistedVotes": 756357.0486175116, "nonBlacklistedVotesBreakdowns": [], "totalDeposited": 29698.444799999997, "dollarPerVote": 0.039265112758958956, "efficiency": 1.7475446173302205, "platform": "convex"}, {"gauge": "0x8f5e52BE9B7BDe850BA13e40284F63f14677058f", "nonBlacklistedVotes": 1507585.1012695075, "nonBlacklistedVotesBreakdowns": [], "totalDeposited": 59156.69760000001, "dollarPerVote": 0.039239375309682564, "efficiency": 1.7486908471208786, "platform": "convex"}, {"gauge": "0xB1A829a05E618F7C4f50Cb86f8F64Fb86e42dE5a", "nonBlacklistedVotes": 59769.65487079194, "nonBlacklistedVotesBreakdowns": [], "totalDeposited": 0.0, "dollarPerVote": 0.0, "efficiency": -1, "platform": "votemarket"}, {"gauge": "0xa971354DB30DF69b35cf99B434875A32AEA0718A", "nonBlacklistedVotes": 0, "nonBlacklistedVotesBreakdowns": [], "totalDeposited": 215510.31233364373, "dollarPerVote": 0, "efficiency": -1, "platform": "votemarket"}, {"gauge": "0x170100AeD2A922a570E5D105C29cc7158f3de359", "nonBlacklistedVotes": 0, "nonBlacklistedVotesBreakdowns": [], "totalDeposited": 223101.53165901688, "dollarPerVote": 0, "efficiency": -1, "platform": "votemarket"}, {"gauge": "0xDa9A503E67A075AF2c3Ea840256b02891535471A", "nonBlacklistedVotes": 0, "nonBlacklistedVotesBreakdowns": [], "totalDeposited": 0.0, "dollarPerVote": 0, "efficiency": -1, "platform": "votemarket"}, {"gauge": "0x26F7786de3E6D9Bd37Fcf47BE6F2bC455a21b74A", "nonBlacklistedVotes": 0, "nonBlacklistedVotesBreakdowns": [], "totalDeposited": 38863.36248490637, "dollarPerVote": 0, "efficiency": -1, "platform": "votemarket"}, {"gauge": "0xd8b712d29381748dB89c36BCa0138d7c75866ddF", "nonBlacklistedVotes": 1208908.940773365, "nonBlacklistedVotesBreakdowns": [], "totalDeposited": 185856.65455531076, "dollarPerVote": 0.026564667124881224, "efficiency": 2.58303769169062, "platform": "votemarket"}, {"gauge": "0x8B0aBcFC78a5c14520682FCD76A0E52B71126079", "nonBlacklistedVotes": 0, "nonBlacklistedVotesBreakdowns": [], "totalDeposited": 55947.54, "dollarPerVote": 0, "efficiency": -1, "platform": "votemarket"}, {"gauge": "0xd51E1Eee15eF7dc924AAA8B82ff2D2E73408F58c", "nonBlacklistedVotes": 911.2217684174542, "nonBlacklistedVotesBreakdowns": [], "totalDeposited": 55947.54, "dollarPerVote": 0.02732954671630342, "efficiency": 2.5107455005775545, "platform": "votemarket"}, {"gauge": "0xEcAD6745058377744c09747b2715c0170B5699e5", "nonBlacklistedVotes": 0, "nonBlacklistedVotesBreakdowns": [], "totalDeposited": 17283.0, "dollarPerVote": 0, "efficiency": -1, "platform": "votemarket"}, {"gauge": "0x4Fc86cd0F9b650280Fa783e3116258e0E0496A2c", "nonBlacklistedVotes": 0, "nonBlacklistedVotesBreakdowns": [], "totalDeposited": 19752.0, "dollarPerVote": 0, "efficiency": -1, "platform": "votemarket"}, {"gauge": "0x30e06CADFbC54d61B7821dC1e58026bf3435d2Fe", "nonBlacklistedVotes": 43118.39270258788, "nonBlacklistedVotesBreakdowns": [], "totalDeposited": 14814.0, "dollarPerVote": 0.02705374433081049, "efficiency": 2.5363415729717294, "platform": "votemarket"}, {"gauge": "0x7671299eA7B4bbE4f3fD305A994e6443b4be680E", "nonBlacklistedVotes": 0, "nonBlacklistedVotesBreakdowns": [], "totalDeposited": 9920.0, "dollarPerVote": 0, "efficiency": -1, "platform": "votemarket"}]}