[{"id": 120, "nonBlacklistedVotes": 0, "totalDeposited": 3561.8760330000005, "dollarPerVote": 0, "incentiveDirected": 0.0, "incentiveDirectedUSD": 0.0, "efficiency": -1}, {"id": 121, "nonBlacklistedVotes": 966517.3733434839, "totalDeposited": 4543.161965333333, "dollarPerVote": 0, "incentiveDirected": 4783.178010438857, "incentiveDirectedUSD": 2702.476443185913, "efficiency": -1}, {"id": 122, "nonBlacklistedVotes": 961843.0513844618, "totalDeposited": 4561.535949910036, "dollarPerVote": 0, "incentiveDirected": 4785.812993148925, "incentiveDirectedUSD": 2586.674493041076, "efficiency": -1}, {"id": 123, "nonBlacklistedVotes": 1683233.2718599034, "totalDeposited": 3176.61422715394, "dollarPerVote": 0, "incentiveDirected": 8345.708340529589, "incentiveDirectedUSD": 3735.1331504003238, "efficiency": -1}, {"id": 124, "nonBlacklistedVotes": 1675140.8042067306, "totalDeposited": 3392.893938918263, "dollarPerVote": 0, "incentiveDirected": 8347.416897355197, "incentiveDirectedUSD": 3792.192374655414, "efficiency": -1}, {"id": 125, "nonBlacklistedVotes": 1513261.5896390232, "totalDeposited": 3859.917912693849, "dollarPerVote": 0, "incentiveDirected": 7531.165921329885, "incentiveDirectedUSD": 3654.317515343215, "efficiency": -1}, {"id": 126, "nonBlacklistedVotes": 1505915.6595922317, "totalDeposited": 4034.819925158118, "dollarPerVote": 0, "incentiveDirected": 7530.910603447616, "incentiveDirectedUSD": 3946.0841925474992, "efficiency": -1}, {"id": 127, "nonBlacklistedVotes": 1518833.6386453023, "totalDeposited": 2336.4712408806445, "dollarPerVote": 0, "incentiveDirected": 7541.266315644569, "incentiveDirectedUSD": 4130.562716535368, "efficiency": -1}, {"id": 128, "nonBlacklistedVotes": 1511496.2780721367, "totalDeposited": 3130.3966460492748, "dollarPerVote": 0, "incentiveDirected": 7531.247497136643, "incentiveDirectedUSD": 4510.900938389969, "efficiency": -1}, {"id": 129, "nonBlacklistedVotes": 833084.2013026234, "totalDeposited": 3367.855723056557, "dollarPerVote": 0, "incentiveDirected": 4143.94032096356, "incentiveDirectedUSD": 3325.43751664748, "efficiency": -1}, {"id": 130, "nonBlacklistedVotes": 829023.1465201315, "totalDeposited": 2620.206614941422, "dollarPerVote": 0, "incentiveDirected": 4145.915507415146, "incentiveDirectedUSD": 3579.3968829044034, "efficiency": -1}, {"id": 131, "nonBlacklistedVotes": 785961.4238341488, "totalDeposited": 2707.933804053454, "dollarPerVote": 0, "incentiveDirected": 3920.9454820509022, "incentiveDirectedUSD": 2633.6755546206987, "efficiency": -1}]