[{"roundDetails": {"id": 192, "startTimestamp": 1747267200, "endTimestamp": 1747872000}, "analytic": {"gauge": "0x6e69796d3d091f0ef0266a96d6dc68e991381d56", "nonBlacklistedVotes": 0.0, "nonBlacklistedVotesBreakdowns": [{"key": "42161-8c2c-14d9-113", "nonBlacklistedVotes": 0.0}], "totalDeposited": 432.23048199786666, "dollarPerVote": 0.00169496263, "incentiveDirected": 0.0, "incentiveDirectedUSD": 0.0, "efficiency": 1.4767732383793009, "platform": "votemarket"}}, {"roundDetails": {"id": 193, "startTimestamp": 1747872000, "endTimestamp": 1748476800}, "analytic": {"gauge": "0x6e69796d3d091f0ef0266a96d6dc68e991381d56", "nonBlacklistedVotes": 359511.0424739522, "nonBlacklistedVotesBreakdowns": [{"key": "42161-8c2c-14d9-113", "nonBlacklistedVotes": 359511.0424739522}], "totalDeposited": 612.9502731392, "dollarPerVote": 0.00160242872, "incentiveDirected": 1195.8963766207037, "incentiveDirectedUSD": 909.6179183997331, "efficiency": 1.578948817486516, "platform": "votemarket"}}, {"roundDetails": {"id": 194, "startTimestamp": 1748476800, "endTimestamp": 1749081600}, "analytic": {"gauge": "0x6e69796d3d091f0ef0266a96d6dc68e991381d56", "nonBlacklistedVotes": 359511.0424739522, "nonBlacklistedVotesBreakdowns": [{"key": "42161-8c2c-14d9-113", "nonBlacklistedVotes": 359511.0424739522}], "totalDeposited": 171.15725770282748, "dollarPerVote": 0.0004760834508031235, "incentiveDirected": 1201.8159869540318, "incentiveDirectedUSD": 788.0920352610932, "efficiency": 4.604490898244125, "platform": "votemarket"}}]