[{"roundDetails": {"id": 219, "startTimestamp": 1763596800, "endTimestamp": 1764201600}, "analytic": {"gauge": "0xe1bdb9973080741e864eb2483abcc86925f97356", "nonBlacklistedVotes": 626723.188395924, "nonBlacklistedVotesBreakdowns": [{"key": "42161-8c2c-14d9-710", "nonBlacklistedVotes": 626723.188395924}], "totalDeposited": 648.6741564065944, "dollarPerVote": 0.0010127372433268115, "incentiveDirected": 1764.510361793532, "incentiveDirectedUSD": 779.2327458606271, "efficiency": 1.2277067670154305, "platform": "votemarket"}}]