[{"id": 85, "nonBlacklistedVotes": 216495.3191460564, "totalDeposited": 1169.5175, "dollarPerVote": 0, "incentiveDirected": 1457.6343221018458, "incentiveDirectedUSD": 1417.718463825409, "efficiency": -1}, {"id": 86, "nonBlacklistedVotes": 215362.03647433105, "totalDeposited": 1273.3930652552247, "dollarPerVote": 0, "incentiveDirected": 1457.0926635530654, "incentiveDirectedUSD": 1222.274895358171, "efficiency": -1}, {"id": 87, "nonBlacklistedVotes": 49428.01924057299, "totalDeposited": 1306.8119410015302, "dollarPerVote": 0, "incentiveDirected": 332.65665101170003, "incentiveDirectedUSD": 278.0610414476598, "efficiency": -1}, {"id": 88, "nonBlacklistedVotes": 49106.562847478344, "totalDeposited": 2218.1855226412354, "dollarPerVote": 0, "incentiveDirected": 332.1480149062329, "incentiveDirectedUSD": 275.7625678957508, "efficiency": -1}, {"id": 89, "nonBlacklistedVotes": 640668.651426622, "totalDeposited": 2494.892660030349, "dollarPerVote": 0, "incentiveDirected": 4293.166809148344, "incentiveDirectedUSD": 3509.071409459109, "efficiency": -1}, {"id": 90, "nonBlacklistedVotes": 637459.9582287846, "totalDeposited": 1952.7603880077927, "dollarPerVote": 0, "incentiveDirected": 4176.944373731082, "incentiveDirectedUSD": 3165.760441127645, "efficiency": -1}, {"id": 91, "nonBlacklistedVotes": 9.589041095890234, "totalDeposited": 2470.5068791914873, "dollarPerVote": 0, "incentiveDirected": 0.061566529691607946, "incentiveDirectedUSD": 0.035100864006546745, "efficiency": -1}, {"id": 92, "nonBlacklistedVotes": 19040.282897471756, "totalDeposited": 2730.050224961798, "dollarPerVote": 0, "incentiveDirected": 122.82743354662215, "incentiveDirectedUSD": 84.58597190391616, "efficiency": -1}, {"id": 93, "nonBlacklistedVotes": 390003.8684474339, "totalDeposited": 2883.435253976629, "dollarPerVote": 0, "incentiveDirected": 2492.5868413729268, "incentiveDirectedUSD": 1645.9149134427366, "efficiency": -1}, {"id": 94, "nonBlacklistedVotes": 388088.17034476134, "totalDeposited": 3795.2872630474635, "dollarPerVote": 0, "incentiveDirected": 2479.391459814517, "incentiveDirectedUSD": 1938.621306080212, "efficiency": -1}, {"id": 95, "nonBlacklistedVotes": 503024.83262641606, "totalDeposited": 2350.0746062353005, "dollarPerVote": 0, "incentiveDirected": 3189.684209938641, "incentiveDirectedUSD": 2505.347031748935, "efficiency": -1}, {"id": 96, "nonBlacklistedVotes": 500533.50713268766, "totalDeposited": 2377.7690881269627, "dollarPerVote": 0, "incentiveDirected": 3190.036396500041, "incentiveDirectedUSD": 2485.2138048753395, "efficiency": -1}, {"id": 97, "nonBlacklistedVotes": 222753.3539955799, "totalDeposited": 1771.3066086903011, "dollarPerVote": 0, "incentiveDirected": 1412.5484692059324, "incentiveDirectedUSD": 1030.985226510149, "efficiency": -1}, {"id": 98, "nonBlacklistedVotes": 221611.48353931904, "totalDeposited": 2595.118777435684, "dollarPerVote": 0, "incentiveDirected": 1406.4768436927175, "incentiveDirectedUSD": 818.9338005316779, "efficiency": -1}, {"id": 99, "nonBlacklistedVotes": 868282.1635753801, "totalDeposited": 2974.698682427893, "dollarPerVote": 0, "incentiveDirected": 5351.98373934818, "incentiveDirectedUSD": 3282.9442896023493, "efficiency": -1}, {"id": 100, "nonBlacklistedVotes": 864088.6479509727, "totalDeposited": 2801.2136679337223, "dollarPerVote": 0, "incentiveDirected": 4489.135549181063, "incentiveDirectedUSD": 2426.110796781959, "efficiency": -1}, {"id": 105, "nonBlacklistedVotes": 0, "totalDeposited": 605.8499999999999, "dollarPerVote": 0, "incentiveDirected": 0.0, "incentiveDirectedUSD": 0.0, "efficiency": -1}, {"id": 106, "nonBlacklistedVotes": 0, "totalDeposited": 588.0, "dollarPerVote": 0, "incentiveDirected": 0.0, "incentiveDirectedUSD": 0.0, "efficiency": -1}]