[{"roundDetails": {"id": 94, "startTimestamp": 1768435200, "endTimestamp": 1769644800}, "analytic": {"nonBlacklistedVotes": 2457954.519120124, "nonBlacklistedVotesBreakdowns": [], "totalDeposited": 677.298342530484, "dollarPerVote": 0.00018248736437764495, "incentiveDirected": 0.0, "incentiveDirectedUSD": 0.0, "efficiency": 5.963762193948054, "platform": "votemarket"}}, {"roundDetails": {"id": 95, "startTimestamp": 1769644800, "endTimestamp": 1770854400}, "analytic": {"gauge": "0x1dA19f38Eb6F2c22199dC0848118b26095C29aEd", "nonBlacklistedVotes": 6346317.116626597, "nonBlacklistedVotesBreakdowns": [], "totalDeposited": 1418.4041558354756, "dollarPerVote": 0.00020494638521505553, "incentiveDirected": 0.0, "incentiveDirectedUSD": 0.0, "efficiency": 2.3451686255985167, "platform": "votemarket"}}]