{"number": 105, "endVoting": 1695168000, "totalDepositedUSD": 14055.227154731894, "globalAverageDollarPerVote": 0.0, "globalAverageEfficiency": 0, "analytics": [{"gauge": "0x9b8aed182b8a9430c14e97bf2c02f129f2b36854", "nonBlacklistedVotes": 3241684.806236331, "totalDeposited": 0.0, "dollarPerVote": 0, "incentiveDirected": 2017.6142031191098, "incentiveDirectedUSD": 10558.021665612967, "efficiency": -1}, {"gauge": "0x7af00cf8d3a8a75210a5ed74f2254e2ec43b5b5b", "nonBlacklistedVotes": 4920357.997386384, "totalDeposited": 0.0, "dollarPerVote": 0, "incentiveDirected": 3062.4150012546665, "incentiveDirectedUSD": 16025.384774928725, "efficiency": -1}, {"gauge": "0x9c8d9667d5726aeca4d24171958bee9f46861bed", "nonBlacklistedVotes": 525620.6628554411, "totalDeposited": 2132.448301302144, "dollarPerVote": 0, "incentiveDirected": 327.14461097199734, "incentiveDirectedUSD": 1711.92286666658, "efficiency": -1}, {"gauge": "0x39cd4db6460d8b5961f73e997e86ddbb7ca4d5f6", "nonBlacklistedVotes": 372924.0973096931, "totalDeposited": 4082.5988572143888, "dollarPerVote": 0, "incentiveDirected": 232.10675941409087, "incentiveDirectedUSD": 1214.5970180229335, "efficiency": -1}, {"gauge": "0x10460d02226d6ef7b2419ae150e6377bdbb7ef16", "nonBlacklistedVotes": 4644121.2821813105, "totalDeposited": 7496.581288606898, "dollarPerVote": 0, "incentiveDirected": 2890.4861576642843, "incentiveDirectedUSD": 15125.694213291716, "efficiency": -1}, {"gauge": "0x698137c473bc1f0ea9b85ade45caf64ef2df48d6", "nonBlacklistedVotes": 159091.79066581637, "totalDeposited": 343.5987076084646, "dollarPerVote": 0, "incentiveDirected": 99.01821911540966, "incentiveDirectedUSD": 518.1548093261465, "efficiency": -1}]}