{"totalDepositedUSD": 17958.206484106806, "globalAverageDollarPerVote": 0.0001642480915321038, "globalAverageEfficiency": 0.6942111854957645, "analytics": [{"gauge": "0xfefafb9446d84a9e58a3a2f2dddd7219e8c94fbb", "nonBlacklistedVotes": 8978933.557295265, "nonBlacklistedVotesBreakdowns": [], "totalDeposited": 1829.973551433484, "dollarPerVote": 0.00020380744993336706, "incentiveDirected": 0.0, "incentiveDirectedUSD": 0.0, "efficiency": 0.5594636622714103, "platform": "votium"}, {"gauge": "0xb5152d159fce50a7576eba7fab61c2b98f0ed692", "nonBlacklistedVotes": 3353631.683649779, "nonBlacklistedVotesBreakdowns": [], "totalDeposited": 366.3354874843567, "dollarPerVote": 0.00010923545637715095, "incentiveDirected": 0.0, "incentiveDirectedUSD": 0.0, "efficiency": 1.043826483813447, "platform": "votium"}, {"gauge": "0xa5250c540914e012e22e623275e290c4dc993d11", "nonBlacklistedVotes": 8004719.266328721, "nonBlacklistedVotesBreakdowns": [], "totalDeposited": 851.0252541607507, "dollarPerVote": 0.00010631544041032488, "incentiveDirected": 0.0, "incentiveDirectedUSD": 0.0, "efficiency": 1.0724957908074964, "platform": "votium"}, {"gauge": "0x2122a2bee97545595550b85379AC7676Fd21a5B4", "nonBlacklistedVotes": 7928398.331091717, "nonBlacklistedVotesBreakdowns": [], "totalDeposited": 4999.620537216399, "dollarPerVote": 0.0002234957751890103, "incentiveDirected": 0.0, "incentiveDirectedUSD": 0.0, "efficiency": 0.5101790503265198, "platform": "votemarket"}, {"gauge": "0x6FcFe767c479ef1f2d8c7A4b27e2aBaDD355910F", "nonBlacklistedVotes": 4094393.702126627, "nonBlacklistedVotesBreakdowns": [], "totalDeposited": 886.484639750782, "dollarPerVote": 0.00020550966440407192, "incentiveDirected": 0.0, "incentiveDirectedUSD": 0.0, "efficiency": 0.5548296848644916, "platform": "votemarket"}, {"gauge": "0xA5250C540914E012E22e623275E290c4dC993D11", "nonBlacklistedVotes": 8004719.266328721, "nonBlacklistedVotesBreakdowns": [], "totalDeposited": 886.484639750782, "dollarPerVote": 0.00011003509638902454, "incentiveDirected": 0.0, "incentiveDirectedUSD": 0.0, "efficiency": 1.0362408547796016, "platform": "votemarket"}, {"gauge": "0x288810cdbdFEd9EA3Be3cA4E421Ab795FD0669f3", "nonBlacklistedVotes": 413030.9436355466, "nonBlacklistedVotesBreakdowns": [], "totalDeposited": 147.74743995846367, "dollarPerVote": 0.0002245081246059416, "incentiveDirected": 0.0, "incentiveDirectedUSD": 0.0, "efficiency": 0.507878556903241, "platform": "votemarket"}, {"gauge": "0xA3c0f7360b922136cc8B89063BE1e8daF70427bD", "nonBlacklistedVotes": 2451248.8611415997, "nonBlacklistedVotesBreakdowns": [], "totalDeposited": 482.3681094737788, "dollarPerVote": 0.00019011901114445012, "incentiveDirected": 0.0, "incentiveDirectedUSD": 0.0, "efficiency": 0.5997446633639676, "platform": "votemarket"}, {"gauge": "0x695C6F5ed9CEB6709E00C08e1326710F3169B922", "nonBlacklistedVotes": 0.0, "nonBlacklistedVotesBreakdowns": [], "totalDeposited": 7508.166824878006, "dollarPerVote": 0.0, "incentiveDirected": 0.0, "incentiveDirectedUSD": 0.0, "efficiency": 0.0, "platform": "votemarket"}]}